cs/service_api.py
cs.service_api-20241007.dist-info/METADATA
cs.service_api-20241007.dist-info/WHEEL
cs.service_api-20241007.dist-info/top_level.txt
cs.service_api-20241007.dist-info/RECORD
