Metadata-Version: 2.1
Name: cs.service_api
Version: 20241007
Summary: ServiceAPI, a base class for APIs which talk to a service, typically a web service via HTTP.
Author-email: Cameron Simpson <cs@cskk.id.au>
License: GNU General Public License v3 or later (GPLv3+)
Project-URL: Monorepo Hg/Mercurial Mirror, https://hg.sr.ht/~cameron-simpson/css
Project-URL: Monorepo Git Mirror, https://github.com/cameron-simpson/css
Project-URL: MonoRepo Commits, https://bitbucket.org/cameron_simpson/css/commits/branch/main
Project-URL: Source, https://github.com/cameron-simpson/css/blob/main/lib/python/cs/service_api.py
Keywords: python3
Classifier: Development Status :: 3 - Alpha
Classifier: Programming Language :: Python
Classifier: Programming Language :: Python :: 3
Classifier: Intended Audience :: Developers
Classifier: Operating System :: OS Independent
Classifier: Topic :: Software Development :: Libraries :: Python Modules
Classifier: License :: OSI Approved :: GNU General Public License v3 or later (GPLv3+)
Requires-Dist: cs.deco >=20241007
Requires-Dist: cs.fstags >=20241005
Requires-Dist: cs.logutils >=20241007
Requires-Dist: cs.pfx >=20240630
Requires-Dist: cs.resources >=20241005
Requires-Dist: cs.sqltags >=20240723
Requires-Dist: cs.upd >=20240630
Requires-Dist: icontract
Requires-Dist: requests
